pytblocklib/__init__.py
pytblocklib/exceptions.py
pytblocklib/watcher.py
pytblocklib/blocker/__init__.py
pytblocklib/blocker/blocker.py
pytblocklib/blocker/serializer.py
pytblocklib/browser_cookie3/__init__.py
pytblocklib/chat/__init__.py
pytblocklib/chat/exceptions.py
pytblocklib/chat/tokenlist.py
pytblocklib/chat/core_multithread/__init__.py
pytblocklib/chat/core_multithread/buffer.py
pytblocklib/chat/core_multithread/livechat.py
pytblocklib/chat/paramgen/__init__.py
pytblocklib/chat/paramgen/arcparam.py
pytblocklib/chat/paramgen/liveparam.py
pytblocklib/chat/parser/__init__.py
pytblocklib/chat/parser/live.py
pytblocklib/chat/processors/__init__.py
pytblocklib/chat/processors/default/__init__.py
pytblocklib/chat/processors/default/processor.py
pytblocklib/chat/processors/default/renderer/__init__.py
pytblocklib/chat/processors/default/renderer/base.py
pytblocklib/chat/processors/default/renderer/legacypaid.py
pytblocklib/chat/processors/default/renderer/paidmessage.py
pytblocklib/chat/processors/default/renderer/textmessage.py
pytblocklib/config/__init__.py
pytblocklib/config/config.py
pytblocklib/config/mylogger.py
pytblocklib/http/__init__.py
pytblocklib/http/request.py
pytblocklib/util/__init__.py
pytblocklib-0.1.8.dist-info/LICENSE
pytblocklib-0.1.8.dist-info/METADATA
pytblocklib-0.1.8.dist-info/WHEEL
pytblocklib-0.1.8.dist-info/top_level.txt
pytblocklib-0.1.8.dist-info/RECORD
