Metadata-Version: 2.1
Name: pytblocklib
Version: 0.1.8
Summary: a python library for youtube blocking function.
Home-page: https://github.com/taizan-hokuto/pytblocklib
Author: taizan-hokuto
Author-email: 55448286+taizan-hokuto@users.noreply.github.com
License: GNU Lesser General Public License v3 (LGPLv3)
Keywords: youtube livechat antispam
Platform: UNKNOWN
Classifier: Natural Language :: Japanese
Classifier: Development Status :: 4 - Beta
Classifier: Programming Language :: Python
Classifier: Programming Language :: Python :: 3.7
Classifier: Programming Language :: Python :: 3.8
Classifier: License :: OSI Approved :: GNU Lesser General Public License v3 (LGPLv3)
Requires-Dist: pytz
Requires-Dist: requests
Requires-Dist: urllib3
Requires-Dist: pyaes
Requires-Dist: pbkdf2
Requires-Dist: keyring (==19.2.0)
Requires-Dist: lz4
Requires-Dist: pycryptodome
Requires-Dist: secretstorage (==3.1.2)
